turing_data_transformation/__init__.py
turing_data_transformation/convolution.py
turing_data_transformation/transpose.py
turing_data_transformation/windowing.py
turing_data_transformation-0.1.0.dist-info/METADATA
turing_data_transformation-0.1.0.dist-info/WHEEL
turing_data_transformation-0.1.0.dist-info/RECORD
